Metadata-Version: 2.1
Name: checkme
Version: 0.0.2
Summary: Simple library that thought in Dev Plus.
Home-page: UNKNOWN
Author: Amirhossein Mohammadi
Author-email: amirhosseinmohammadi1380@yahoo.com
License: UNKNOWN
Platform: UNKNOWN
